spotmax_agent/__init__.py
spotmax_agent/agent.py
spotmax_agent/basemodule.py
spotmax_agent/maxgroup_cmd.py
spotmax_agent/scheduler.py
spotmax_agent/taskmanager.py
spotmax_agent/utils.py
spotmax_agent-0.0.8.dist-info/LICENSE
spotmax_agent-0.0.8.dist-info/METADATA
spotmax_agent-0.0.8.dist-info/WHEEL
spotmax_agent-0.0.8.dist-info/entry_points.txt
spotmax_agent-0.0.8.dist-info/top_level.txt
spotmax_agent-0.0.8.dist-info/RECORD
