Metadata-Version: 2.1
Name: spotmax-agent
Version: 0.0.8
Summary: spotmax agent package
Home-page: https://github.com/pypa/sampleproject
Author: liuzoxan
Author-email: liuzoxan@gmail.com
License: UNKNOWN
Platform: UNKNOWN
Classifier: Programming Language :: Python :: 3
Classifier: License :: OSI Approved :: MIT License
Classifier: Operating System :: OS Independent
